singularitytechnologiesapi/__init__.py
singularitytechnologiesapi/data.py
singularitytechnologiesapi/exceptions.py
singularitytechnologies.singularitytechnologiesapi-0.2.4.dev0.dist-info/METADATA
singularitytechnologies.singularitytechnologiesapi-0.2.4.dev0.dist-info/WHEEL
singularitytechnologies.singularitytechnologiesapi-0.2.4.dev0.dist-info/top_level.txt
singularitytechnologies.singularitytechnologiesapi-0.2.4.dev0.dist-info/RECORD
